animals/__init__.py
animals/snake.py
animalk-0.0.0.dist-info/METADATA
animalk-0.0.0.dist-info/WHEEL
animalk-0.0.0.dist-info/top_level.txt
animalk-0.0.0.dist-info/RECORD
